ytthumb.py
YTThumb-1.4.5.dist-info/LICENSE
YTThumb-1.4.5.dist-info/METADATA
YTThumb-1.4.5.dist-info/WHEEL
YTThumb-1.4.5.dist-info/top_level.txt
YTThumb-1.4.5.dist-info/RECORD
