Metadata-Version: 2.1
Name: YTThumb
Version: 1.4.5
Summary: YouTube video thumbnail downloader
Home-page: UNKNOWN
Author: Fayas Noushad
License: MIT
Project-URL: Tracker, https://github.com/FayasNoushad/Youtube-Video-Thumbnail/issues
Project-URL: Source, https://github.com/FayasNoushad/Youtube-Video-Thumbnail
Platform: UNKNOWN
Classifier: Intended Audience :: Developers
Classifier: Natural Language :: English
Classifier: Programming Language :: Python
Classifier: License :: OSI Approved :: MIT License
Classifier: Operating System :: OS Independent
Requires-Python: >=3.6
License-File: LICENSE
Requires-Dist: requests
